firefly_survey/__init__.py
firefly_survey/application/__init__.py
firefly_survey/application/create_document.py
firefly_survey/domain/__init__.py
firefly_survey/domain/entity/__init__.py
firefly_survey/domain/entity/document.py
firefly_survey/domain/entity/schema.py
firefly_survey/infrastructure/__init__.py
firefly_survey/presentation/__init__.py
firefly_survey-0.1.8.dist-info/COPYING
firefly_survey-0.1.8.dist-info/METADATA
firefly_survey-0.1.8.dist-info/WHEEL
firefly_survey-0.1.8.dist-info/top_level.txt
firefly_survey-0.1.8.dist-info/RECORD
