Metadata-Version: 2.1
Name: firefly-survey
Version: 0.1.8
Summary: Bounded context for dealing with subjective inputs from users.
Home-page: https://github.com/firefly-framework/firefly-survey
Author: JD Williams
Author-email: me@jdwilliams.xyz
License: UNKNOWN
Platform: UNKNOWN
Classifier: Programming Language :: Python :: 3.7
Classifier: Operating System :: OS Independent
Requires-Dist: firefly-framework (>=1.1.10)
